palworld_coord/__init__.py
palworld_coord-1.0.0.dist-info/LICENSE
palworld_coord-1.0.0.dist-info/METADATA
palworld_coord-1.0.0.dist-info/WHEEL
palworld_coord-1.0.0.dist-info/top_level.txt
palworld_coord-1.0.0.dist-info/RECORD
