Metadata-Version: 2.1
Name: palworld-coord
Version: 1.0.0
Summary: A library to convert coordinates in Palworld from the .sav file to Paldex Map and vice-versa
Author-email: Robert Bost <bostrt@gmail.com>
Maintainer-email: Robert Bost <bostrt@gmail.com>
License: MIT License
Project-URL: Homepage, https://github.com/palworldlol/palworld-coord
Classifier: Intended Audience :: Developers
Classifier: Intended Audience :: System Administrators
Classifier: License :: OSI Approved :: MIT License
Classifier: Programming Language :: Python :: 3
Classifier: Programming Language :: Python :: 3.9
Classifier: Programming Language :: Python :: 3.10
Classifier: Programming Language :: Python :: 3.11
Classifier: Programming Language :: Python :: 3 :: Only
Classifier: Topic :: System :: Monitoring
Classifier: Topic :: Games/Entertainment
Requires-Python: >=3.9
License-File: LICENSE
Provides-Extra: test
Requires-Dist: flake8; extra == "test"
Requires-Dist: pytest; extra == "test"
